papersweep/__init__.py
papersweep/_nbdev.py
papersweep/cli.py
papersweep-0.0.3.dist-info/DESCRIPTION.rst
papersweep-0.0.3.dist-info/METADATA
papersweep-0.0.3.dist-info/RECORD
papersweep-0.0.3.dist-info/WHEEL
papersweep-0.0.3.dist-info/entry_points.txt
papersweep-0.0.3.dist-info/metadata.json
papersweep-0.0.3.dist-info/top_level.txt
