Metadata-Version: 2.0
Name: papersweep
Version: 0.0.3
Summary: Combining papermill and wandb sweeps for frictionless experiments with Notebooks
Home-page: https://github.com/vrodriguezf/papersweep/tree/master/
Author: Victor Rodriguez-Fernandez
Author-email: victor.rfernandez@upm.es
License: Apache Software License 2.0
Keywords: papermill wandb sweep Jupyter
Platform: UNKNOWN
Classifier: Development Status :: 3 - Alpha
Classifier: Intended Audience :: Developers
Classifier: License :: OSI Approved :: Apache Software License
Classifier: Natural Language :: English
Classifier: Programming Language :: Python :: 3.6
Classifier: Programming Language :: Python :: 3.7
Classifier: Programming Language :: Python :: 3.8
Requires-Python: >=3.6
Requires-Dist: fastcore
Requires-Dist: numpy
Requires-Dist: papermill
Requires-Dist: wandb
